turtlethread/__init__.py
turtlethread/base_turtle.py
turtlethread/pattern_info.py
turtlethread/stitches.py
turtlethread/turtle.py
turtlethread/visualise.py
turtlethread/sphinx_plugins/__init__.py
turtlethread/sphinx_plugins/manual_example_code_directive.py
turtlethread/sphinx_plugins/turtlethread_gallery_scraper.py
turtlethread-0.0.11.dist-info/AUTHORS.rst
turtlethread-0.0.11.dist-info/LICENSE
turtlethread-0.0.11.dist-info/METADATA
turtlethread-0.0.11.dist-info/WHEEL
turtlethread-0.0.11.dist-info/top_level.txt
turtlethread-0.0.11.dist-info/RECORD
