Metadata-Version: 2.1
Name: turtlethread
Version: 0.0.11
Summary: A Turtle-interface for making embroidery files
Home-page: https://github.com/marieroald/turtlethread
Author: Marie Roald & Yngve Mardal Moe
Author-email: yngve.m.moe@gmail.com
License: "GNU General Public License v3",
Keywords: turtlethread
Platform: UNKNOWN
Classifier: Development Status :: 2 - Pre-Alpha
Classifier: Intended Audience :: Developers
Classifier: License :: OSI Approved :: GNU General Public License v3 (GPLv3)
Classifier: Natural Language :: English
Classifier: Programming Language :: Python :: 3.6
Classifier: Programming Language :: Python :: 3.7
Classifier: Programming Language :: Python :: 3.8
Classifier: Programming Language :: Python :: 3.9
License-File: LICENSE
License-File: AUTHORS.rst
Requires-Dist: pyembroidery
Requires-Dist: typing-extensions ; python_version < "3.11"
Provides-Extra: dev
Requires-Dist: black ; extra == 'dev'
Requires-Dist: isort ; extra == 'dev'
Requires-Dist: pytest ; extra == 'dev'
Requires-Dist: pytest-coverage ; extra == 'dev'
Requires-Dist: pytest-randomly ; extra == 'dev'
Provides-Extra: docs
Requires-Dist: Jinja2 (>=3.0) ; extra == 'docs'
Requires-Dist: matplotlib ; extra == 'docs'
Requires-Dist: numpydoc ; extra == 'docs'
Requires-Dist: pydata-sphinx-theme (==0.15.2) ; extra == 'docs'
Requires-Dist: sphinx-gallery ; extra == 'docs'
Requires-Dist: sphinx-toolbox ; extra == 'docs'
Requires-Dist: sphinx (==7.2.6) ; extra == 'docs'
Requires-Dist: sphinx-book-theme (==1.1.0) ; extra == 'docs'
